codpypyd.cp39-win_amd64.pyd
codpydll/__init__.py
codpydll/__pycache__/__init__.cpython-39.pyc
codpydll-0.2.dist-info/METADATA
codpydll-0.2.dist-info/WHEEL
codpydll-0.2.dist-info/license
codpydll-0.2.dist-info/top_level.txt
codpydll-0.2.dist-info/RECORD
