Metadata-Version: 2.1
Name: codpydll
Version: 0.2
Summary: An RKHS based module for machine learning and data mining
Home-page: https://github.com/johnlem/codpy_alpha
Author: jean-marc mercier
Author-email: jeanmarc.mercier@gmail.com
Maintainer: jean-marc mercier
License: new BSD
Platform: UNKNOWN
Classifier: Development Status :: 2 - Pre-Alpha
Classifier: Environment :: Win32 (MS Windows)
Classifier: Programming Language :: Python :: 3.9
Classifier: License :: Free for non-commercial use
Classifier: Topic :: Scientific/Engineering
Classifier: Operating System :: Microsoft :: Windows :: Windows 11
License-File: license
Requires-Dist: mkl
